{
    "18376": {
        "la": [
            269.5,
            241.5,
            213.5,
            185.5,
            157.5,
            129.5,
            101.0,
            72.0,
            43.0,
            14.0
        ],
        "arexp": [
            282.0,
            757.5,
            1140.0,
            1801.5,
            2532.25000000017,
            2737.41666666649,
            2956.26666666644,
            3623.2904761904,
            4079.5892857143153,
            4267.979761905204
        ],
        "ld": [
            69.0,
            62.0,
            55.0,
            48.0,
            41.0,
            34.0,
            27.0,
            19.5,
            11.5,
            3.5
        ],
        "asexp": [
            995.0,
            1471.0,
            1994.0,
            2586.0,
            3091.0,
            3652.0,
            4178.5,
            4662.5,
            5195.0,
            5987.5
        ],
        "ent": [
            4.06193064206699,
            3.6403780275710096,
            3.2205817971329704,
            2.8001124674550653,
            2.380057516303275,
            1.96043688134064,
            1.5354675613966,
            1.10501399711353,
            0.6750063424904039,
            0.246022578220332
        ],
        "nuc": [
            7.066964285714286,
            6.252659574468085,
            5.402702702702706,
            4.64318181818182,
            3.914545454545455,
            3.233031674208145,
            2.45299145299145,
            1.76388888888889,
            1.095454545454545,
            0.38048245614035103
        ],
        "ns": [
            3,
            2,
            1
        ],
        "age": [
            9.320512820512821,
            7.7729591836734695,
            6.633333333333335,
            5.596296296296295,
            4.35923753665689,
            3.3397435897435903,
            2.42857142857143,
            1.6,
            0.8888888888888891,
            0.260869565217391
        ]
    },
    "18896": {
        "la": [
            269.5,
            241.5,
            213.5,
            185.5,
            157.5,
            129.5,
            101.0,
            72.0,
            43.0,
            14.0
        ],
        "arexp": [
            282.0,
            757.5,
            1140.0,
            1801.5,
            2532.25000000017,
            2737.41666666649,
            2956.26666666644,
            3623.2904761904,
            4079.5892857143153,
            4267.979761905204
        ],
        "ld": [
            69.0,
            62.0,
            55.0,
            48.0,
            41.0,
            34.0,
            27.0,
            19.5,
            11.5,
            3.5
        ],
        "asexp": [
            995.0,
            1471.0,
            1994.0,
            2586.0,
            3091.0,
            3652.0,
            4178.5,
            4662.5,
            5195.0,
            5987.5
        ],
        "ent": [
            4.06193064206699,
            3.6403780275710096,
            3.2205817971329704,
            2.8001124674550653,
            2.380057516303275,
            1.96043688134064,
            1.5354675613966,
            1.10501399711353,
            0.6750063424904039,
            0.246022578220332
        ],
        "nuc": [
            7.066964285714286,
            6.252659574468085,
            5.402702702702706,
            4.64318181818182,
            3.914545454545455,
            3.233031674208145,
            2.45299145299145,
            1.76388888888889,
            1.095454545454545,
            0.38048245614035103
        ],
        "ns": [
            3,
            2,
            1
        ],
        "age": [
            9.320512820512821,
            7.7729591836734695,
            6.633333333333335,
            5.596296296296295,
            4.35923753665689,
            3.3397435897435903,
            2.42857142857143,
            1.6,
            0.8888888888888891,
            0.260869565217391
        ]
    },
    "18909": {
        "la": [
            269.5,
            241.5,
            213.5,
            185.5,
            157.5,
            129.5,
            101.0,
            72.0,
            43.0,
            14.0
        ],
        "arexp": [
            282.0,
            757.5,
            1140.0,
            1801.5,
            2532.25000000017,
            2737.41666666649,
            2956.26666666644,
            3623.2904761904,
            4079.5892857143153,
            4267.979761905204
        ],
        "ld": [
            69.0,
            62.0,
            55.0,
            48.0,
            41.0,
            34.0,
            27.0,
            19.5,
            11.5,
            3.5
        ],
        "asexp": [
            995.0,
            1471.0,
            1994.0,
            2586.0,
            3091.0,
            3652.0,
            4178.5,
            4662.5,
            5195.0,
            5987.5
        ],
        "ent": [
            4.06193064206699,
            3.6403780275710096,
            3.2205817971329704,
            2.8001124674550653,
            2.380057516303275,
            1.96043688134064,
            1.5354675613966,
            1.10501399711353,
            0.6750063424904039,
            0.246022578220332
        ],
        "nuc": [
            7.066964285714286,
            6.252659574468085,
            5.402702702702706,
            4.64318181818182,
            3.914545454545455,
            3.233031674208145,
            2.45299145299145,
            1.76388888888889,
            1.095454545454545,
            0.38048245614035103
        ],
        "ns": [
            3,
            2,
            1
        ],
        "age": [
            9.320512820512821,
            7.7729591836734695,
            6.633333333333335,
            5.596296296296295,
            4.35923753665689,
            3.3397435897435903,
            2.42857142857143,
            1.6,
            0.8888888888888891,
            0.260869565217391
        ]
    },
    "18915": {
        "la": [
            269.5,
            241.5,
            213.5,
            185.5,
            157.5,
            129.5,
            101.0,
            72.0,
            43.0,
            14.0
        ],
        "arexp": [
            282.0,
            757.5,
            1140.0,
            1801.5,
            2532.25000000017,
            2737.41666666649,
            2956.26666666644,
            3623.2904761904,
            4079.5892857143153,
            4267.979761905204
        ],
        "ld": [
            69.0,
            62.0,
            55.0,
            48.0,
            41.0,
            34.0,
            27.0,
            19.5,
            11.5,
            3.5
        ],
        "asexp": [
            995.0,
            1471.0,
            1994.0,
            2586.0,
            3091.0,
            3652.0,
            4178.5,
            4662.5,
            5195.0,
            5987.5
        ],
        "ent": [
            4.06193064206699,
            3.6403780275710096,
            3.2205817971329704,
            2.8001124674550653,
            2.380057516303275,
            1.96043688134064,
            1.5354675613966,
            1.10501399711353,
            0.6750063424904039,
            0.246022578220332
        ],
        "nuc": [
            7.066964285714286,
            6.252659574468085,
            5.402702702702706,
            4.64318181818182,
            3.914545454545455,
            3.233031674208145,
            2.45299145299145,
            1.76388888888889,
            1.095454545454545,
            0.38048245614035103
        ],
        "ns": [
            3,
            2,
            1
        ],
        "age": [
            9.320512820512821,
            7.7729591836734695,
            6.633333333333335,
            5.596296296296295,
            4.35923753665689,
            3.3397435897435903,
            2.42857142857143,
            1.6,
            0.8888888888888891,
            0.260869565217391
        ]
    },
    "19000": {
        "la": [
            269.5,
            241.5,
            213.5,
            185.5,
            157.5,
            129.5,
            101.0,
            72.0,
            43.0,
            14.0
        ],
        "arexp": [
            282.0,
            757.5,
            1140.0,
            1801.5,
            2532.25000000017,
            2737.41666666649,
            2956.26666666644,
            3623.2904761904,
            4079.5892857143153,
            4267.979761905204
        ],
        "ld": [
            69.0,
            62.0,
            55.0,
            48.0,
            41.0,
            34.0,
            27.0,
            19.5,
            11.5,
            3.5
        ],
        "asexp": [
            995.0,
            1471.0,
            1994.0,
            2586.0,
            3091.0,
            3652.0,
            4178.5,
            4662.5,
            5195.0,
            5987.5
        ],
        "ent": [
            4.06193064206699,
            3.6403780275710096,
            3.2205817971329704,
            2.8001124674550653,
            2.380057516303275,
            1.96043688134064,
            1.5354675613966,
            1.10501399711353,
            0.6750063424904039,
            0.246022578220332
        ],
        "nuc": [
            7.066964285714286,
            6.252659574468085,
            5.402702702702706,
            4.64318181818182,
            3.914545454545455,
            3.233031674208145,
            2.45299145299145,
            1.76388888888889,
            1.095454545454545,
            0.38048245614035103
        ],
        "ns": [
            3,
            2,
            1
        ],
        "age": [
            9.320512820512821,
            7.7729591836734695,
            6.633333333333335,
            5.596296296296295,
            4.35923753665689,
            3.3397435897435903,
            2.42857142857143,
            1.6,
            0.8888888888888891,
            0.260869565217391
        ]
    },
    "19102": {
        "la": [
            269.5,
            241.5,
            213.5,
            185.5,
            157.5,
            129.5,
            101.0,
            72.0,
            43.0,
            14.0
        ],
        "arexp": [
            282.0,
            757.5,
            1140.0,
            1801.5,
            2532.25000000017,
            2737.41666666649,
            2956.26666666644,
            3623.2904761904,
            4079.5892857143153,
            4267.979761905204
        ],
        "ld": [
            69.0,
            62.0,
            55.0,
            48.0,
            41.0,
            34.0,
            27.0,
            19.5,
            11.5,
            3.5
        ],
        "asexp": [
            995.0,
            1471.0,
            1994.0,
            2586.0,
            3091.0,
            3652.0,
            4178.5,
            4662.5,
            5195.0,
            5987.5
        ],
        "ent": [
            4.06193064206699,
            3.6403780275710096,
            3.2205817971329704,
            2.8001124674550653,
            2.380057516303275,
            1.96043688134064,
            1.5354675613966,
            1.10501399711353,
            0.6750063424904039,
            0.246022578220332
        ],
        "nuc": [
            7.066964285714286,
            6.252659574468085,
            5.402702702702706,
            4.64318181818182,
            3.914545454545455,
            3.233031674208145,
            2.45299145299145,
            1.76388888888889,
            1.095454545454545,
            0.38048245614035103
        ],
        "ns": [
            3,
            2,
            1
        ],
        "age": [
            9.320512820512821,
            7.7729591836734695,
            6.633333333333335,
            5.596296296296295,
            4.35923753665689,
            3.3397435897435903,
            2.42857142857143,
            1.6,
            0.8888888888888891,
            0.260869565217391
        ]
    },
    "19125": {
        "la": [
            269.5,
            241.5,
            213.5,
            185.5,
            157.5,
            129.5,
            101.0,
            72.0,
            43.0,
            14.0
        ],
        "arexp": [
            282.0,
            757.5,
            1140.0,
            1801.5,
            2532.25000000017,
            2737.41666666649,
            2956.26666666644,
            3623.2904761904,
            4079.5892857143153,
            4267.979761905204
        ],
        "ld": [
            69.0,
            62.0,
            55.0,
            48.0,
            41.0,
            34.0,
            27.0,
            19.5,
            11.5,
            3.5
        ],
        "asexp": [
            995.0,
            1471.0,
            1994.0,
            2586.0,
            3091.0,
            3652.0,
            4178.5,
            4662.5,
            5195.0,
            5987.5
        ],
        "ent": [
            4.06193064206699,
            3.6403780275710096,
            3.2205817971329704,
            2.8001124674550653,
            2.380057516303275,
            1.96043688134064,
            1.5354675613966,
            1.10501399711353,
            0.6750063424904039,
            0.246022578220332
        ],
        "nuc": [
            7.066964285714286,
            6.252659574468085,
            5.402702702702706,
            4.64318181818182,
            3.914545454545455,
            3.233031674208145,
            2.45299145299145,
            1.76388888888889,
            1.095454545454545,
            0.38048245614035103
        ],
        "ns": [
            3,
            2,
            1
        ],
        "age": [
            9.320512820512821,
            7.7729591836734695,
            6.633333333333335,
            5.596296296296295,
            4.35923753665689,
            3.3397435897435903,
            2.42857142857143,
            1.6,
            0.8888888888888891,
            0.260869565217391
        ]
    },
    "19142": {
        "la": [
            269.5,
            241.5,
            213.5,
            185.5,
            157.5,
            129.5,
            101.0,
            72.0,
            43.0,
            14.0
        ],
        "arexp": [
            282.0,
            757.5,
            1140.0,
            1801.5,
            2532.25000000017,
            2737.41666666649,
            2956.26666666644,
            3623.2904761904,
            4079.5892857143153,
            4267.979761905204
        ],
        "ld": [
            69.0,
            62.0,
            55.0,
            48.0,
            41.0,
            34.0,
            27.0,
            19.5,
            11.5,
            3.5
        ],
        "asexp": [
            995.0,
            1471.0,
            1994.0,
            2586.0,
            3091.0,
            3652.0,
            4178.5,
            4662.5,
            5195.0,
            5987.5
        ],
        "ent": [
            4.06193064206699,
            3.6403780275710096,
            3.2205817971329704,
            2.8001124674550653,
            2.380057516303275,
            1.96043688134064,
            1.5354675613966,
            1.10501399711353,
            0.6750063424904039,
            0.246022578220332
        ],
        "nuc": [
            7.066964285714286,
            6.252659574468085,
            5.402702702702706,
            4.64318181818182,
            3.914545454545455,
            3.233031674208145,
            2.45299145299145,
            1.76388888888889,
            1.095454545454545,
            0.38048245614035103
        ],
        "ns": [
            3,
            2,
            1
        ],
        "age": [
            9.320512820512821,
            7.7729591836734695,
            6.633333333333335,
            5.596296296296295,
            4.35923753665689,
            3.3397435897435903,
            2.42857142857143,
            1.6,
            0.8888888888888891,
            0.260869565217391
        ]
    },
    "19184": {
        "la": [
            269.5,
            241.5,
            213.5,
            185.5,
            157.5,
            129.5,
            101.0,
            72.0,
            43.0,
            14.0
        ],
        "arexp": [
            282.0,
            757.5,
            1140.0,
            1801.5,
            2532.25000000017,
            2737.41666666649,
            2956.26666666644,
            3623.2904761904,
            4079.5892857143153,
            4267.979761905204
        ],
        "ld": [
            69.0,
            62.0,
            55.0,
            48.0,
            41.0,
            34.0,
            27.0,
            19.5,
            11.5,
            3.5
        ],
        "asexp": [
            995.0,
            1471.0,
            1994.0,
            2586.0,
            3091.0,
            3652.0,
            4178.5,
            4662.5,
            5195.0,
            5987.5
        ],
        "ent": [
            4.06193064206699,
            3.6403780275710096,
            3.2205817971329704,
            2.8001124674550653,
            2.380057516303275,
            1.96043688134064,
            1.5354675613966,
            1.10501399711353,
            0.6750063424904039,
            0.246022578220332
        ],
        "nuc": [
            7.066964285714286,
            6.252659574468085,
            5.402702702702706,
            4.64318181818182,
            3.914545454545455,
            3.233031674208145,
            2.45299145299145,
            1.76388888888889,
            1.095454545454545,
            0.38048245614035103
        ],
        "ns": [
            3,
            2,
            1
        ],
        "age": [
            9.320512820512821,
            7.7729591836734695,
            6.633333333333335,
            5.596296296296295,
            4.35923753665689,
            3.3397435897435903,
            2.42857142857143,
            1.6,
            0.8888888888888891,
            0.260869565217391
        ]
    },
    "19236": {
        "la": [
            269.5,
            241.5,
            213.5,
            185.5,
            157.5,
            129.5,
            101.0,
            72.0,
            43.0,
            14.0
        ],
        "arexp": [
            282.0,
            757.5,
            1140.0,
            1801.5,
            2532.25000000017,
            2737.41666666649,
            2956.26666666644,
            3623.2904761904,
            4079.5892857143153,
            4267.979761905204
        ],
        "ld": [
            69.0,
            62.0,
            55.0,
            48.0,
            41.0,
            34.0,
            27.0,
            19.5,
            11.5,
            3.5
        ],
        "asexp": [
            995.0,
            1471.0,
            1994.0,
            2586.0,
            3091.0,
            3652.0,
            4178.5,
            4662.5,
            5195.0,
            5987.5
        ],
        "ent": [
            4.06193064206699,
            3.6403780275710096,
            3.2205817971329704,
            2.8001124674550653,
            2.380057516303275,
            1.96043688134064,
            1.5354675613966,
            1.10501399711353,
            0.6750063424904039,
            0.246022578220332
        ],
        "nuc": [
            7.066964285714286,
            6.252659574468085,
            5.402702702702706,
            4.64318181818182,
            3.914545454545455,
            3.233031674208145,
            2.45299145299145,
            1.76388888888889,
            1.095454545454545,
            0.38048245614035103
        ],
        "ns": [
            3,
            2,
            1
        ],
        "age": [
            9.320512820512821,
            7.7729591836734695,
            6.633333333333335,
            5.596296296296295,
            4.35923753665689,
            3.3397435897435903,
            2.42857142857143,
            1.6,
            0.8888888888888891,
            0.260869565217391
        ]
    },
    "19565": {
        "la": [
            269.5,
            241.5,
            213.5,
            185.5,
            157.5,
            129.5,
            101.0,
            72.0,
            43.0,
            14.0
        ],
        "arexp": [
            282.0,
            757.5,
            1140.0,
            1801.5,
            2532.25000000017,
            2737.41666666649,
            2956.26666666644,
            3623.2904761904,
            4079.5892857143153,
            4267.979761905204
        ],
        "ld": [
            69.0,
            62.0,
            55.0,
            48.0,
            41.0,
            34.0,
            27.0,
            19.5,
            11.5,
            3.5
        ],
        "asexp": [
            995.0,
            1471.0,
            1994.0,
            2586.0,
            3091.0,
            3652.0,
            4178.5,
            4662.5,
            5195.0,
            5987.5
        ],
        "ent": [
            4.06193064206699,
            3.6403780275710096,
            3.2205817971329704,
            2.8001124674550653,
            2.380057516303275,
            1.96043688134064,
            1.5354675613966,
            1.10501399711353,
            0.6750063424904039,
            0.246022578220332
        ],
        "nuc": [
            7.066964285714286,
            6.252659574468085,
            5.402702702702706,
            4.64318181818182,
            3.914545454545455,
            3.233031674208145,
            2.45299145299145,
            1.76388888888889,
            1.095454545454545,
            0.38048245614035103
        ],
        "ns": [
            3,
            2,
            1
        ],
        "age": [
            9.320512820512821,
            7.7729591836734695,
            6.633333333333335,
            5.596296296296295,
            4.35923753665689,
            3.3397435897435903,
            2.42857142857143,
            1.6,
            0.8888888888888891,
            0.260869565217391
        ]
    },
    "19634": {
        "la": [
            269.5,
            241.5,
            213.5,
            185.5,
            157.5,
            129.5,
            101.0,
            72.0,
            43.0,
            14.0
        ],
        "arexp": [
            282.0,
            757.5,
            1140.0,
            1801.5,
            2532.25000000017,
            2737.41666666649,
            2956.26666666644,
            3623.2904761904,
            4079.5892857143153,
            4267.979761905204
        ],
        "ld": [
            69.0,
            62.0,
            55.0,
            48.0,
            41.0,
            34.0,
            27.0,
            19.5,
            11.5,
            3.5
        ],
        "asexp": [
            995.0,
            1471.0,
            1994.0,
            2586.0,
            3091.0,
            3652.0,
            4178.5,
            4662.5,
            5195.0,
            5987.5
        ],
        "ent": [
            4.06193064206699,
            3.6403780275710096,
            3.2205817971329704,
            2.8001124674550653,
            2.380057516303275,
            1.96043688134064,
            1.5354675613966,
            1.10501399711353,
            0.6750063424904039,
            0.246022578220332
        ],
        "nuc": [
            7.066964285714286,
            6.252659574468085,
            5.402702702702706,
            4.64318181818182,
            3.914545454545455,
            3.233031674208145,
            2.45299145299145,
            1.76388888888889,
            1.095454545454545,
            0.38048245614035103
        ],
        "ns": [
            3,
            2,
            1
        ],
        "age": [
            9.320512820512821,
            7.7729591836734695,
            6.633333333333335,
            5.596296296296295,
            4.35923753665689,
            3.3397435897435903,
            2.42857142857143,
            1.6,
            0.8888888888888891,
            0.260869565217391
        ]
    },
    "20180": {
        "la": [
            269.5,
            241.5,
            213.5,
            185.5,
            157.5,
            129.5,
            101.0,
            72.0,
            43.0,
            14.0
        ],
        "arexp": [
            282.0,
            757.5,
            1140.0,
            1801.5,
            2532.25000000017,
            2737.41666666649,
            2956.26666666644,
            3623.2904761904,
            4079.5892857143153,
            4267.979761905204
        ],
        "ld": [
            69.0,
            62.0,
            55.0,
            48.0,
            41.0,
            34.0,
            27.0,
            19.5,
            11.5,
            3.5
        ],
        "asexp": [
            995.0,
            1471.0,
            1994.0,
            2586.0,
            3091.0,
            3652.0,
            4178.5,
            4662.5,
            5195.0,
            5987.5
        ],
        "ent": [
            4.06193064206699,
            3.6403780275710096,
            3.2205817971329704,
            2.8001124674550653,
            2.380057516303275,
            1.96043688134064,
            1.5354675613966,
            1.10501399711353,
            0.6750063424904039,
            0.246022578220332
        ],
        "nuc": [
            7.066964285714286,
            6.252659574468085,
            5.402702702702706,
            4.64318181818182,
            3.914545454545455,
            3.233031674208145,
            2.45299145299145,
            1.76388888888889,
            1.095454545454545,
            0.38048245614035103
        ],
        "ns": [
            3,
            2,
            1
        ],
        "age": [
            9.320512820512821,
            7.7729591836734695,
            6.633333333333335,
            5.596296296296295,
            4.35923753665689,
            3.3397435897435903,
            2.42857142857143,
            1.6,
            0.8888888888888891,
            0.260869565217391
        ]
    },
    "20249": {
        "la": [
            269.5,
            241.5,
            213.5,
            185.5,
            157.5,
            129.5,
            101.0,
            72.0,
            43.0,
            14.0
        ],
        "arexp": [
            282.0,
            757.5,
            1140.0,
            1801.5,
            2532.25000000017,
            2737.41666666649,
            2956.26666666644,
            3623.2904761904,
            4079.5892857143153,
            4267.979761905204
        ],
        "ld": [
            69.0,
            62.0,
            55.0,
            48.0,
            41.0,
            34.0,
            27.0,
            19.5,
            11.5,
            3.5
        ],
        "asexp": [
            995.0,
            1471.0,
            1994.0,
            2586.0,
            3091.0,
            3652.0,
            4178.5,
            4662.5,
            5195.0,
            5987.5
        ],
        "ent": [
            4.06193064206699,
            3.6403780275710096,
            3.2205817971329704,
            2.8001124674550653,
            2.380057516303275,
            1.96043688134064,
            1.5354675613966,
            1.10501399711353,
            0.6750063424904039,
            0.246022578220332
        ],
        "nuc": [
            7.066964285714286,
            6.252659574468085,
            5.402702702702706,
            4.64318181818182,
            3.914545454545455,
            3.233031674208145,
            2.45299145299145,
            1.76388888888889,
            1.095454545454545,
            0.38048245614035103
        ],
        "ns": [
            3,
            2,
            1
        ],
        "age": [
            9.320512820512821,
            7.7729591836734695,
            6.633333333333335,
            5.596296296296295,
            4.35923753665689,
            3.3397435897435903,
            2.42857142857143,
            1.6,
            0.8888888888888891,
            0.260869565217391
        ]
    },
    "20570": {
        "la": [
            269.5,
            241.5,
            213.5,
            185.5,
            157.5,
            129.5,
            101.0,
            72.0,
            43.0,
            14.0
        ],
        "arexp": [
            282.0,
            757.5,
            1140.0,
            1801.5,
            2532.25000000017,
            2737.41666666649,
            2956.26666666644,
            3623.2904761904,
            4079.5892857143153,
            4267.979761905204
        ],
        "ld": [
            69.0,
            62.0,
            55.0,
            48.0,
            41.0,
            34.0,
            27.0,
            19.5,
            11.5,
            3.5
        ],
        "asexp": [
            995.0,
            1471.0,
            1994.0,
            2586.0,
            3091.0,
            3652.0,
            4178.5,
            4662.5,
            5195.0,
            5987.5
        ],
        "ent": [
            4.06193064206699,
            3.6403780275710096,
            3.2205817971329704,
            2.8001124674550653,
            2.380057516303275,
            1.96043688134064,
            1.5354675613966,
            1.10501399711353,
            0.6750063424904039,
            0.246022578220332
        ],
        "nuc": [
            7.066964285714286,
            6.252659574468085,
            5.402702702702706,
            4.64318181818182,
            3.914545454545455,
            3.233031674208145,
            2.45299145299145,
            1.76388888888889,
            1.095454545454545,
            0.38048245614035103
        ],
        "ns": [
            3,
            2,
            1
        ],
        "age": [
            9.320512820512821,
            7.7729591836734695,
            6.633333333333335,
            5.596296296296295,
            4.35923753665689,
            3.3397435897435903,
            2.42857142857143,
            1.6,
            0.8888888888888891,
            0.260869565217391
        ]
    },
    "21395": {
        "la": [
            269.5,
            241.5,
            213.5,
            185.5,
            157.5,
            129.5,
            101.0,
            72.0,
            43.0,
            14.0
        ],
        "arexp": [
            282.0,
            757.5,
            1140.0,
            1801.5,
            2532.25000000017,
            2737.41666666649,
            2956.26666666644,
            3623.2904761904,
            4079.5892857143153,
            4267.979761905204
        ],
        "ld": [
            69.0,
            62.0,
            55.0,
            48.0,
            41.0,
            34.0,
            27.0,
            19.5,
            11.5,
            3.5
        ],
        "asexp": [
            995.0,
            1471.0,
            1994.0,
            2586.0,
            3091.0,
            3652.0,
            4178.5,
            4662.5,
            5195.0,
            5987.5
        ],
        "ent": [
            4.06193064206699,
            3.6403780275710096,
            3.2205817971329704,
            2.8001124674550653,
            2.380057516303275,
            1.96043688134064,
            1.5354675613966,
            1.10501399711353,
            0.6750063424904039,
            0.246022578220332
        ],
        "nuc": [
            7.066964285714286,
            6.252659574468085,
            5.402702702702706,
            4.64318181818182,
            3.914545454545455,
            3.233031674208145,
            2.45299145299145,
            1.76388888888889,
            1.095454545454545,
            0.38048245614035103
        ],
        "ns": [
            3,
            2,
            1
        ],
        "age": [
            9.320512820512821,
            7.7729591836734695,
            6.633333333333335,
            5.596296296296295,
            4.35923753665689,
            3.3397435897435903,
            2.42857142857143,
            1.6,
            0.8888888888888891,
            0.260869565217391
        ]
    },
    "21445": {
        "la": [
            269.5,
            241.5,
            213.5,
            185.5,
            157.5,
            129.5,
            101.0,
            72.0,
            43.0,
            14.0
        ],
        "arexp": [
            282.0,
            757.5,
            1140.0,
            1801.5,
            2532.25000000017,
            2737.41666666649,
            2956.26666666644,
            3623.2904761904,
            4079.5892857143153,
            4267.979761905204
        ],
        "ld": [
            69.0,
            62.0,
            55.0,
            48.0,
            41.0,
            34.0,
            27.0,
            19.5,
            11.5,
            3.5
        ],
        "asexp": [
            995.0,
            1471.0,
            1994.0,
            2586.0,
            3091.0,
            3652.0,
            4178.5,
            4662.5,
            5195.0,
            5987.5
        ],
        "ent": [
            4.06193064206699,
            3.6403780275710096,
            3.2205817971329704,
            2.8001124674550653,
            2.380057516303275,
            1.96043688134064,
            1.5354675613966,
            1.10501399711353,
            0.6750063424904039,
            0.246022578220332
        ],
        "nuc": [
            7.066964285714286,
            6.252659574468085,
            5.402702702702706,
            4.64318181818182,
            3.914545454545455,
            3.233031674208145,
            2.45299145299145,
            1.76388888888889,
            1.095454545454545,
            0.38048245614035103
        ],
        "ns": [
            3,
            2,
            1
        ],
        "age": [
            9.320512820512821,
            7.7729591836734695,
            6.633333333333335,
            5.596296296296295,
            4.35923753665689,
            3.3397435897435903,
            2.42857142857143,
            1.6,
            0.8888888888888891,
            0.260869565217391
        ]
    },
    "21934": {
        "la": [
            269.5,
            241.5,
            213.5,
            185.5,
            157.5,
            129.5,
            101.0,
            72.0,
            43.0,
            14.0
        ],
        "arexp": [
            282.0,
            757.5,
            1140.0,
            1801.5,
            2532.25000000017,
            2737.41666666649,
            2956.26666666644,
            3623.2904761904,
            4079.5892857143153,
            4267.979761905204
        ],
        "ld": [
            69.0,
            62.0,
            55.0,
            48.0,
            41.0,
            34.0,
            27.0,
            19.5,
            11.5,
            3.5
        ],
        "asexp": [
            995.0,
            1471.0,
            1994.0,
            2586.0,
            3091.0,
            3652.0,
            4178.5,
            4662.5,
            5195.0,
            5987.5
        ],
        "ent": [
            4.06193064206699,
            3.6403780275710096,
            3.2205817971329704,
            2.8001124674550653,
            2.380057516303275,
            1.96043688134064,
            1.5354675613966,
            1.10501399711353,
            0.6750063424904039,
            0.246022578220332
        ],
        "nuc": [
            7.066964285714286,
            6.252659574468085,
            5.402702702702706,
            4.64318181818182,
            3.914545454545455,
            3.233031674208145,
            2.45299145299145,
            1.76388888888889,
            1.095454545454545,
            0.38048245614035103
        ],
        "ns": [
            3,
            2,
            1
        ],
        "age": [
            9.320512820512821,
            7.7729591836734695,
            6.633333333333335,
            5.596296296296295,
            4.35923753665689,
            3.3397435897435903,
            2.42857142857143,
            1.6,
            0.8888888888888891,
            0.260869565217391
        ]
    },
    "22227": {
        "la": [
            269.5,
            241.5,
            213.5,
            185.5,
            157.5,
            129.5,
            101.0,
            72.0,
            43.0,
            14.0
        ],
        "arexp": [
            282.0,
            757.5,
            1140.0,
            1801.5,
            2532.25000000017,
            2737.41666666649,
            2956.26666666644,
            3623.2904761904,
            4079.5892857143153,
            4267.979761905204
        ],
        "ld": [
            69.0,
            62.0,
            55.0,
            48.0,
            41.0,
            34.0,
            27.0,
            19.5,
            11.5,
            3.5
        ],
        "asexp": [
            995.0,
            1471.0,
            1994.0,
            2586.0,
            3091.0,
            3652.0,
            4178.5,
            4662.5,
            5195.0,
            5987.5
        ],
        "ent": [
            4.06193064206699,
            3.6403780275710096,
            3.2205817971329704,
            2.8001124674550653,
            2.380057516303275,
            1.96043688134064,
            1.5354675613966,
            1.10501399711353,
            0.6750063424904039,
            0.246022578220332
        ],
        "nuc": [
            7.066964285714286,
            6.252659574468085,
            5.402702702702706,
            4.64318181818182,
            3.914545454545455,
            3.233031674208145,
            2.45299145299145,
            1.76388888888889,
            1.095454545454545,
            0.38048245614035103
        ],
        "ns": [
            3,
            2,
            1
        ],
        "age": [
            9.320512820512821,
            7.7729591836734695,
            6.633333333333335,
            5.596296296296295,
            4.35923753665689,
            3.3397435897435903,
            2.42857142857143,
            1.6,
            0.8888888888888891,
            0.260869565217391
        ]
    }
}